{
  "version": 4,
  "migration": "patch",
  "binaries": {
    "liquid-signet": {
      "type": "sidechain",
      "slot": 24,
      "name": "Liquid Signet",
      "version": "b7da9f75ea1d3da7a0b761cd7f18d81500bb1011",
      "description": "Elements/Liquid sidechain in slot 24.",
      "repo_url": "https://github.com/ekulkisnek/liquid-drivechain-signet-adaptation",
      "port": 29443,
      "chain_layer": 2,
      "color": "blue",
      "health_check": {"type": "tcp"},
      "dependencies": ["bitcoind", "enforcer"],
      "startup_log_patterns": ["Done loading"],
      "directories": {"binary": {"default": {"linux": "liquid-signet", "macos": "liquid-signet", "windows": "liquid-signet"}}, "flutter_frontend": {}},
      "download": {"binary": "liquid-signet", "files": {"default": {"base_url": "https://github.com/ekulkisnek/liquid-drivechain-signet-adaptation/releases/download/liquid-signet-b7da9f75/", "linux-x86_64": "", "macos-x86_64": "", "macos-arm64": "liquid-signet-b7da9f75-macos-arm64.tar.gz", "windows-x86_64": ""}}},
      "hashes": {}
    }
  }
}
